[
{"title": "[新聞] OP", "author": "Axwell", "date": " 3/16", "url": "/bbs/Baseball/M.1710572888.A.93F.html"},
{"title": "[新聞] MLB》何時傷癒復出還是未知數！ 洋基重", "author": "Toyosushij", "date": " 3/16", "url": "/bbs/Baseball/M.1710573251.A.AFD.html"},
{"title": "[新聞] 影／連4局1出局讓對手上壘　上澤直之守", "author": "Toyosushij", "date": " 3/16", "url": "/bbs/Baseball/M.1710573408.A.334.html"},
{"title": "[新聞] 中職／全壘打版圖拚收集第15座球場 林智", "author": "Toyosushij", "date": " 3/16", "url": "/bbs/Baseball/M.1710573749.A.39A.html"},
{"title": "[新聞] 中山穩守強勢扣倒新明 挑戰連霸剩一步", "author": "ZaneTrout", "date": " 3/16", "url": "/bbs/Baseball/M.1710574316.A.244.html"},
{"title": "[情報] 教士派Cease出戰LG & 道奇派Miller對韓", "author": "zxc906383", "date": " 3/16", "url": "/bbs/Baseball/M.1710574490.A.273.html"},
{"title": "[公告] 板規", "author": "TRosenthal", "date": "10/14", "url": "/bbs/Baseball/M.1634212242.A.283.html"},
{"title": "[整理] 2024棒球賽事轉播節目表", "author": "johnnyckvs", "date": " 1/01", "url": "/bbs/Baseball/M.1704038825.A.DE5.html"},
{"title": "[LIVE] NPB熱身賽　歐力士 v 羅德", "author": "YuiiAnitima", "date": " 3/16", "url": "/bbs/Baseball/M.1710559134.A.F88.html"},
{"title": "[LIVE] NPB熱身賽　巨人 v 火腿", "author": "YuiiAnitima", "date": " 3/16", "url": "/bbs/Baseball/M.1710562568.A.43C.html"}
]